wiggle_api/__init__.py
wiggle_api/main.py
wiggle_api-1.1.2.dist-info/entry_points.txt
wiggle_api-1.1.2.dist-info/WHEEL
wiggle_api-1.1.2.dist-info/METADATA
wiggle_api-1.1.2.dist-info/RECORD
