Metadata-Version: 2.3
Name: wiggle-api
Version: 1.1.2
Summary: Basic API for WiggleBin.
Requires-Dist: flask
